setup.py
dig/__init__.py
dig/framer/__init__.py
dig/framer/framer.py
dig/io/__init__.py
dig/io/adapter/__init__.py
dig/io/adapter/hbase_adapter.py
dig/io/adapter/key_value_adapter.py
dig/io/adapter/memory_adapter.py
dig/io/serializer/__init__.py
dig/io/serializer/pickle_serializer.py
dig/io/serializer/serializer.py
dig/reducer/__init__.py
dig/reducer/jsonld_comparator.py
dig/reducer/jsonld_reducer.py
dig/tests/__init__.py
dig/tests/test_data_types.py
dig/tests/test_reducer.py
dig/utils/__init__.py
dig/utils/data_types.py
dig/utils/jsonld_util.py
dig_reducer.egg-info/PKG-INFO
dig_reducer.egg-info/SOURCES.txt
dig_reducer.egg-info/dependency_links.txt
dig_reducer.egg-info/requires.txt
dig_reducer.egg-info/top_level.txt