Metadata-Version: 1.0
Name: dig-reducer
Version: 1.0
Summary: JSONLD Reducer and Framer
Home-page: https://github.com/usc-isi-i2/dig-reducer
Author: USC/ISI
Author-email: UNKNOWN
License: MIT
Platform: UNKNOWN
